{
  "step": 26042,
  "query": [
    "20968",
    "21269"
  ],
  "response": [
    " members may have a facility to view the material that is available will be able to",
    " arresting plant arresting plant's natural world would be on the one that is the most"
  ],
  "victim_response": [
    " members may have a facility to view the material that is available will be able to",
    " arresting plant arresting plant's natural world would be on the one that is the most"
  ],
  "rewards": [
    1.0,
    1.0
  ]
}