{
  "step": 23433,
  "query": [
    "20559",
    "20925"
  ],
  "response": [
    " carboneded might be the solar radiation produced by the wind turbine's solar wind turbine",
    " clearing part check out the J cell in the Advanced loan initiator flight of the"
  ],
  "victim_response": [
    " carboneded might be the solar radiation produced by the wind turbine's solar wind turbine",
    " clearing part check out the J cell in the Advanced loan initiator flight of the"
  ],
  "rewards": [
    1.0,
    1.0
  ]
}