{
  "step": 18607,
  "query": [
    "21546",
    "20144"
  ],
  "response": [
    " contact is silent there is a physical statement is a physical motion is motion is motion",
    " trial was a failure trial may continue if the trial is a failure trial does not"
  ],
  "victim_response": [
    " contact is silent there is a physical statement is a physical motion is motion is motion",
    " trial was a failure trial may continue if the trial is a failure trial does not"
  ],
  "rewards": [
    1.0,
    1.0
  ]
}