{
  "step": 25652,
  "query": [
    "21974",
    "21550"
  ],
  "response": [
    " Mar will be among the most coordinated, if not the most, those forces involved",
    " refers to the time period in the previous class railway passenger vehicle class to the class"
  ],
  "victim_response": [
    " Mar will be among the most coordinated, if not the most, those forces involved",
    " refers to the time period in the previous class railway passenger vehicle class to the class"
  ],
  "rewards": [
    1.0,
    1.0
  ]
}