{
  "step": 17151,
  "query": [
    "21888",
    "20042"
  ],
  "response": [
    " D electric D counter D electric D electric D electric D electric D electric D electric",
    " Full custody denies it's legal actions unreasonable and denies that they are legal and the"
  ],
  "victim_response": [
    " D electric D counter D electric D electric D electric D electric D electric D electric",
    " Full custody denies it's legal actions unreasonable and denies that they are legal and the"
  ],
  "rewards": [
    1.0,
    1.0
  ]
}