{
  "step": 26464,
  "query": [
    "20663",
    "21126"
  ],
  "response": [
    " criminal-lock-up Law school wanted buzzing the drug background investigation would be the",
    " might be a contender, but there was a fight between them and the prime of"
  ],
  "victim_response": [
    " criminal-lock-up Law school wanted buzzing the drug background investigation would be the",
    " might be a contender, but there was a fight between them and the prime of"
  ],
  "rewards": [
    1.0,
    1.0
  ]
}