{
  "step": 15439,
  "query": [
    "21658",
    "20155"
  ],
  "response": [
    " centers Sunny valley valley valley valley valley valley valley valley valley valley valley valley valley valley",
    "D painting a scene. The lighted man's body is covered in a dr"
  ],
  "victim_response": [
    " centers Sunny valley valley valley valley valley valley valley valley valley valley valley valley valley valley",
    "D painting a scene. The lighted man's body is covered in a dr"
  ],
  "rewards": [
    1.0,
    1.0
  ]
}