{
  "step": 26266,
  "query": [
    "21125",
    "21303"
  ],
  "response": [
    " competition circuit circuits and probably world circuit circuit competition circuits companies competed in competition circuit circuits",
    " could be a great application for the program.\"\n\nThe UNC of the south"
  ],
  "victim_response": [
    " competition circuit circuits and probably world circuit circuit competition circuits companies competed in competition circuit circuits",
    " could be a great application for the program.\"\n\nThe UNC of the south"
  ],
  "rewards": [
    1.0,
    1.0
  ]
}