{
  "step": 26542,
  "query": [
    "21984",
    "21924"
  ],
  "response": [
    " actually means a railroad transporting rail service railway transport set up conducted in Texas and used",
    " does the prosecution of the defendant's client come in a very hostile place, has"
  ],
  "victim_response": [
    " actually means a railroad transporting rail service railway transport set up conducted in Texas and used",
    " does the prosecution of the defendant's client come in a very hostile place, has"
  ],
  "rewards": [
    1.0,
    1.0
  ]
}