{
  "step": 23401,
  "query": [
    "20916",
    "20655"
  ],
  "response": [
    " will was the attorney for the area in an affidavit filed with the Office of the",
    " star principal principal cell number joined means they are number of cells found per cell per"
  ],
  "victim_response": [
    " will was the attorney for the area in an affidavit filed with the Office of the",
    " star principal principal cell number joined means they are number of cells found per cell per"
  ],
  "rewards": [
    1.0,
    1.0
  ]
}