{
  "step": 25367,
  "query": [
    "21119",
    "21739"
  ],
  "response": [
    " labour movement workers group occupied people workers rally strikers strikers union laborers union workers union workers",
    " may be brought a charge the way the previous part did, by the effect of"
  ],
  "victim_response": [
    " labour movement workers group occupied people workers rally strikers strikers union laborers union workers union workers",
    " may be brought a charge the way the previous part did, by the effect of"
  ],
  "rewards": [
    1.0,
    1.0
  ]
}