{
  "step": 20538,
  "query": [
    "20045",
    "21669"
  ],
  "response": [
    " has been published in the mainstream media since the 1970s, and will be published",
    " reg reg number Phrav round Registration R F stay place Cell charge Fee Recharge"
  ],
  "victim_response": [
    " has been published in the mainstream media since the 1970s, and will be published",
    " reg reg number Phrav round Registration R F stay place Cell charge Fee Recharge"
  ],
  "rewards": [
    1.0,
    1.0
  ]
}