{
  "step": 26898,
  "query": [
    "20708",
    "20418"
  ],
  "response": [
    " might have the forest covered by the damages amount, the person is likely to be",
    "141 may be responsible for the resumption of its employment of people under the agreement"
  ],
  "victim_response": [
    " might have the forest covered by the damages amount, the person is likely to be",
    "141 may be responsible for the resumption of its employment of people under the agreement"
  ],
  "rewards": [
    1.0,
    1.0
  ]
}