{
  "step": 20579,
  "query": [
    "21692",
    "20178"
  ],
  "response": [
    " is the head of the ICC Rule 1 court in the United States of America central",
    " surveillance bill does not provide immunity for children under 21 years of age \u2013 if the"
  ],
  "victim_response": [
    " is the head of the ICC Rule 1 court in the United States of America central",
    " surveillance bill does not provide immunity for children under 21 years of age \u2013 if the"
  ],
  "rewards": [
    1.0,
    1.0
  ]
}