{
  "step": 24928,
  "query": [
    "21652",
    "21938"
  ],
  "response": [
    " Rothschilds air space for the powerful British satanic moths has been silent about",
    " mining scientists laborers class participation income state occupation geographical access oil Waging highway Away"
  ],
  "victim_response": [
    " Rothschilds air space for the powerful British satanic moths has been silent about",
    " mining scientists laborers class participation income state occupation geographical access oil Waging highway Away"
  ],
  "rewards": [
    1.0,
    1.0
  ]
}