{
  "step": 22839,
  "query": [
    "20593",
    "21363"
  ],
  "response": [
    "fee income a living laborer has expenses capital costs cost explosion cost explosion cost cost",
    " alien was blocked all Marches by the court will it be a long process her"
  ],
  "victim_response": [
    "fee income a living laborer has expenses capital costs cost explosion cost explosion cost cost",
    " alien was blocked all Marches by the court will it be a long process her"
  ],
  "rewards": [
    1.0,
    1.0
  ]
}