{
  "step": 21757,
  "query": [
    "20252",
    "21081"
  ],
  "response": [
    " pBend-oped voluntary force certification protest since 1990 or 1991, is not",
    " 82 court opposition disrupted their communication with the government and attempted to go to the right"
  ],
  "victim_response": [
    " pBend-oped voluntary force certification protest since 1990 or 1991, is not",
    " 82 court opposition disrupted their communication with the government and attempted to go to the right"
  ],
  "rewards": [
    1.0,
    1.0
  ]
}