{
  "step": 18866,
  "query": [
    "21669",
    "20067"
  ],
  "response": [
    " th copper oxide oxide deposition catoration deposition deposition deposition deposition deposition deposition deposition deposition",
    " D1 flame, 19 rh rh rh rh rh rh rh rh rh rh rh"
  ],
  "victim_response": [
    " th copper oxide oxide deposition catoration deposition deposition deposition deposition deposition deposition deposition deposition",
    " D1 flame, 19 rh rh rh rh rh rh rh rh rh rh rh"
  ],
  "rewards": [
    1.0,
    1.0
  ]
}