{
  "step": 27520,
  "query": [
    "20559",
    "21772"
  ],
  "response": [
    " Tuesday the firm has been working on two social media accounts \u2014 the university's micro",
    " would be striking the one thing a miner should be able to take away is the"
  ],
  "victim_response": [
    " Tuesday the firm has been working on two social media accounts \u2014 the university's micro",
    " would be striking the one thing a miner should be able to take away is the"
  ],
  "rewards": [
    1.0,
    1.0
  ]
}