{
  "step": 24361,
  "query": [
    "21393",
    "21233"
  ],
  "response": [
    "01 may not contain the producers' production industry's or the ingredient referred to as",
    " has failed may not be part of the public sector drugs resistant public sector is on"
  ],
  "victim_response": [
    "01 may not contain the producers' production industry's or the ingredient referred to as",
    " has failed may not be part of the public sector drugs resistant public sector is on"
  ],
  "rewards": [
    1.0,
    1.0
  ]
}