{
  "step": 24196,
  "query": [
    "21090",
    "20836"
  ],
  "response": [
    " is a a smooth, air cooling radiator that was developed by the Subaru Manufacturing Group",
    " Gh production tax would be dropped if the government buys land tax on a band of"
  ],
  "victim_response": [
    " is a a smooth, air cooling radiator that was developed by the Subaru Manufacturing Group",
    " Gh production tax would be dropped if the government buys land tax on a band of"
  ],
  "rewards": [
    1.0,
    1.0
  ]
}