{
  "step": 27038,
  "query": [
    "21669",
    "20653"
  ],
  "response": [
    " could be bridstrought out without the attempt might be futile. To think that",
    " previous contamination of an air plant over the Federal grid 12 log turbine is supported by"
  ],
  "victim_response": [
    " could be bridstrought out without the attempt might be futile. To think that",
    " previous contamination of an air plant over the Federal grid 12 log turbine is supported by"
  ],
  "rewards": [
    1.0,
    1.0
  ]
}