{
  "step": 17393,
  "query": [
    "20626",
    "20045"
  ],
  "response": [
    "D Marriott Cosby Cosby Cosby Cosby Cosby Cosby Cosby Cosby Cosby Cosby Cosby Cosby Cosby Cosby",
    " profess a performance in the valley next to the largest in the world. The chamber"
  ],
  "victim_response": [
    "D Marriott Cosby Cosby Cosby Cosby Cosby Cosby Cosby Cosby Cosby Cosby Cosby Cosby Cosby Cosby",
    " profess a performance in the valley next to the largest in the world. The chamber"
  ],
  "rewards": [
    1.0,
    1.0
  ]
}