{
  "step": 21267,
  "query": [
    "21291",
    "21672"
  ],
  "response": [
    " taxi queen search ladyz queen spray queen queen bee queen bee queen bee queen bee",
    " Ranged Coil Location hotblocks Ranged attack does damage Ranged damage does damage"
  ],
  "victim_response": [
    " taxi queen search ladyz queen spray queen queen bee queen bee queen bee queen bee",
    " Ranged Coil Location hotblocks Ranged attack does damage Ranged damage does damage"
  ],
  "rewards": [
    1.0,
    1.0
  ]
}