{
  "step": 18504,
  "query": [
    "20401",
    "20000"
  ],
  "response": [
    " patent patent patent patent patent patent patent patent patent patent patent patent patent patent patent patent",
    " return target number airstrike D command D compensation targets 11 Boss pay pay pay pay pay"
  ],
  "victim_response": [
    " patent patent patent patent patent patent patent patent patent patent patent patent patent patent patent patent",
    " return target number airstrike D command D compensation targets 11 Boss pay pay pay pay pay"
  ],
  "rewards": [
    1.0,
    1.0
  ]
}