{
  "step": 20351,
  "query": [
    "20047",
    "20401"
  ],
  "response": [
    " L work was pay as a working child he was entitled to pay as a working",
    " patent number a patent number the number of patent patents patent number number patent number patent"
  ],
  "victim_response": [
    " L work was pay as a working child he was entitled to pay as a working",
    " patent number a patent number the number of patent patents patent number number patent number patent"
  ],
  "rewards": [
    1.0,
    1.0
  ]
}