{
  "step": 21876,
  "query": [
    "20655",
    "20583"
  ],
  "response": [
    "701 used this registrant entry compulsory ring registered required entry registered sex certified witness required",
    " is on the riot registry counters male dying practice k tiger k tiger k tiger k"
  ],
  "victim_response": [
    "701 used this registrant entry compulsory ring registered required entry registered sex certified witness required",
    " is on the riot registry counters male dying practice k tiger k tiger k tiger k"
  ],
  "rewards": [
    1.0,
    1.0
  ]
}