{
  "step": 19779,
  "query": [
    "21368",
    "20445"
  ],
  "response": [
    " there is a flight frequency somewhere there is a location also a rider is someone has",
    " cells King Knight plaintiffs plaintiffs cell King Knight plaintiffs cell plaintiffs cells King Knight plaintiffs plaintiffs"
  ],
  "victim_response": [
    " there is a flight frequency somewhere there is a location also a rider is someone has",
    " cells King Knight plaintiffs plaintiffs cell King Knight plaintiffs cell plaintiffs cells King Knight plaintiffs plaintiffs"
  ],
  "rewards": [
    1.0,
    1.0
  ]
}