{
  "step": 27540,
  "query": [
    "21541",
    "21126"
  ],
  "response": [
    " FARM, FR An actor's head metal helmet causes the head to be covered",
    " witnesses settled court proceedings over the last two decades. And what has been the takeaway"
  ],
  "victim_response": [
    " FARM, FR An actor's head metal helmet causes the head to be covered",
    " witnesses settled court proceedings over the last two decades. And what has been the takeaway"
  ],
  "rewards": [
    1.0,
    1.0
  ]
}